vye_svgbob-0.1.4.dist-info/METADATA
vye_svgbob-0.1.4.dist-info/WHEEL
vye_svgbob-0.1.4.dist-info/license_files/LICENSE
vye_svgbob/__init__.py
vye_svgbob/vye_svgbob.cpython-311-darwin.so
vye_svgbob-0.1.4.dist-info/RECORD
