Metadata-Version: 2.1
Name: vye-svgbob
Version: 0.1.4
Classifier: Programming Language :: Rust
Classifier: Programming Language :: Python :: Implementation :: CPython
Classifier: Programming Language :: Python :: Implementation :: PyPy
License-File: LICENSE
Summary: Render ASCII art diagrams to SVG using the Rust crate svgbob.
Keywords: svgbob,ascii,svg
Requires-Python: >=3.8
Project-URL: Repository, https://github.com/sattva9/vye-svgbob
